ghrm/__init__.py
ghrm/__main__.py
ghrm/cli.py
ghrm/config.toml
ghrm/display.py
ghrm/py.typed
ghrm/repository.py
ghrm/notifications/__init__.py
ghrm/notifications/discord.py
ghrm/notifications/slack.py
github_manager_cli-0.1.dist-info/METADATA
github_manager_cli-0.1.dist-info/WHEEL
github_manager_cli-0.1.dist-info/entry_points.txt
github_manager_cli-0.1.dist-info/licenses/LICENSE
github_manager_cli-0.1.dist-info/licenses/LICENSE.LESSER
github_manager_cli-0.1.dist-info/RECORD
