Metadata-Version: 2.4
Name: github-manager-cli
Version: 0.1
Summary: A tool to manage GitHub objects
Project-URL: Homepage, https://github.com/SLAVNG/github-manager-cli
Author-email: Slav <sosadtsia@gmail.com>
License:                     GNU GENERAL PUBLIC LICENSE
License-File: LICENSE
License-File: LICENSE.LESSER
Keywords: cli,github
Classifier: Development Status :: 4 - Beta
Classifier: Environment :: Console
Classifier: Intended Audience :: Developers
Classifier: Intended Audience :: System Administrators
Classifier: License :: OSI Approved :: GNU Library or Lesser General Public License (LGPL)
Classifier: Operating System :: OS Independent
Classifier: Programming Language :: Python :: 3.11
Classifier: Programming Language :: Python :: 3.12
Classifier: Topic :: Utilities
Requires-Python: >=3.11
Requires-Dist: pygithub
Requires-Dist: python-dotenv
Requires-Dist: pyyaml
Requires-Dist: requests
Requires-Dist: rich
Provides-Extra: dev
Requires-Dist: black; extra == 'dev'
Requires-Dist: pip-tools; extra == 'dev'
Requires-Dist: pytest; extra == 'dev'
Requires-Dist: uv; extra == 'dev'
